{"type":"foundation-effects","styles":[{"name":"Shadows/2xs","effects":[{"type":"DROP_SHADOW","color":"#000000","alpha":0.05,"x":0,"y":1,"radius":0,"spread":0}]},{"name":"Shadows/xs","effects":[{"type":"DROP_SHADOW","color":"#000000","alpha":0.05,"x":0,"y":1,"radius":2,"spread":0}]},{"name":"Shadows/sm","effects":[{"type":"DROP_SHADOW","color":"#000000","alpha":0.1,"x":0,"y":1,"radius":3,"spread":0},{"type":"DROP_SHADOW","color":"#000000","alpha":0.1,"x":0,"y":1,"radius":2,"spread":-1}]},{"name":"Shadows/md","effects":[{"type":"DROP_SHADOW","color":"#000000","alpha":0.1,"x":0,"y":4,"radius":6,"spread":-1},{"type":"DROP_SHADOW","color":"#000000","alpha":0.1,"x":0,"y":2,"radius":4,"spread":-2}]},{"name":"Shadows/lg","effects":[{"type":"DROP_SHADOW","color":"#000000","alpha":0.1,"x":0,"y":10,"radius":15,"spread":-3},{"type":"DROP_SHADOW","color":"#000000","alpha":0.1,"x":0,"y":4,"radius":6,"spread":-4}]},{"name":"Shadows/xl","effects":[{"type":"DROP_SHADOW","color":"#000000","alpha":0.1,"x":0,"y":20,"radius":25,"spread":-5},{"type":"DROP_SHADOW","color":"#000000","alpha":0.1,"x":0,"y":8,"radius":10,"spread":-6}]},{"name":"Shadows/2xl","effects":[{"type":"DROP_SHADOW","color":"#000000","alpha":0.25,"x":0,"y":25,"radius":50,"spread":12}]},{"name":"Glass/card","effects":[{"type":"BACKGROUND_BLUR","radius":12}]},{"name":"Glass/elevated","effects":[{"type":"BACKGROUND_BLUR","radius":16}]},{"name":"Glass/panel","effects":[{"type":"BACKGROUND_BLUR","radius":24}]},{"name":"Glow/accent","effects":[{"type":"DROP_SHADOW","color":"#7c3aed","alpha":0.15,"x":0,"y":0,"radius":0,"spread":1},{"type":"DROP_SHADOW","color":"#7c3aed","alpha":0.25,"x":0,"y":0,"radius":20,"spread":-4},{"type":"DROP_SHADOW","color":"#7c3aed","alpha":0.1,"x":0,"y":0,"radius":40,"spread":-8}]},{"name":"Glow/success","effects":[{"type":"DROP_SHADOW","color":"#22c55e","alpha":0.15,"x":0,"y":0,"radius":0,"spread":1},{"type":"DROP_SHADOW","color":"#22c55e","alpha":0.2,"x":0,"y":0,"radius":20,"spread":-4}]},{"name":"Glow/destructive","effects":[{"type":"DROP_SHADOW","color":"#ef4444","alpha":0.15,"x":0,"y":0,"radius":0,"spread":1},{"type":"DROP_SHADOW","color":"#ef4444","alpha":0.2,"x":0,"y":0,"radius":20,"spread":-4}]},{"name":"Glass/accent","effects":[{"type":"BACKGROUND_BLUR","radius":12}]},{"name":"Ring/default","effects":[{"type":"DROP_SHADOW","color":"#27272a","alpha":1,"x":0,"y":0,"radius":0,"spread":3}]},{"name":"Ring/error","effects":[{"type":"DROP_SHADOW","color":"#7f1d1d","alpha":1,"x":0,"y":0,"radius":0,"spread":3}]},{"name":"Ring/brand","effects":[{"type":"DROP_SHADOW","color":"#4c1d95","alpha":1,"x":0,"y":0,"radius":0,"spread":3}]},{"name":"Ring/success","effects":[{"type":"DROP_SHADOW","color":"#14532d","alpha":1,"x":0,"y":0,"radius":0,"spread":3}]},{"name":"Ring/warning","effects":[{"type":"DROP_SHADOW","color":"#78350f","alpha":1,"x":0,"y":0,"radius":0,"spread":3}]},{"name":"Ring/emphasis","effects":[{"type":"DROP_SHADOW","color":"#1e3a8a","alpha":1,"x":0,"y":0,"radius":0,"spread":3}]}]}